plugnmeet_sdk/PlugNMeet.py
plugnmeet_sdk/__init__.py
plugnmeet_sdk/exceptions.py
plugnmeet_sdk/utils.py
plugnmeet_sdk/schemas/__init__.py
plugnmeet_sdk/schemas/data/__init__.py
plugnmeet_sdk/schemas/data/_data.py
plugnmeet_sdk/schemas/requests/__init__.py
plugnmeet_sdk/schemas/requests/_requests.py
plugnmeet_sdk-1.0.2.dist-info/licenses/LICENSE
plugnmeet_sdk-1.0.2.dist-info/METADATA
plugnmeet_sdk-1.0.2.dist-info/WHEEL
plugnmeet_sdk-1.0.2.dist-info/top_level.txt
plugnmeet_sdk-1.0.2.dist-info/RECORD
