Metadata-Version: 2.4
Name: plugnmeet-sdk
Version: 1.0.2
Summary: Pythonic SDK for PlugNmeet meeting platform
Author-email: vector-mj <mj.hosseini.dev@gmail.com>
Project-URL: Homepage, https://github.com/vector-mj/plugnmeet-sdk
Classifier: Development Status :: 5 - Production/Stable
Classifier: Programming Language :: Python
Classifier: Programming Language :: Python :: 3.10
Requires-Python: >=3.8
License-File: LICENSE
Requires-Dist: aiohttp>=3.12.0
Requires-Dist: attrs>=25.3.0
Dynamic: license-file
